MANIFEST.in
README.md
setup.cfg
setup.py
tyrs
doc/LICENCE
doc/index.txt
doc/quick_start.txt
doc/reference-dev.txt
doc/reference.txt
doc/screenshot.txt
doc/tyrs.1.gz
po/POTFILES.in
po/es.po
po/fr.po
src/tyrs/__init__.py
src/tyrs/completion.py
src/tyrs/config.py
src/tyrs/constant.py
src/tyrs/container.py
src/tyrs/editor.py
src/tyrs/filter.py
src/tyrs/help.py
src/tyrs/interface.py
src/tyrs/keys.py
src/tyrs/message.py
src/tyrs/timeline.py
src/tyrs/tweets.py
src/tyrs/tyrs.py
src/tyrs/update.py
src/tyrs/user.py
src/tyrs/utils.py
src/tyrs/widget.py
src/tyrs/shorter/__init__.py
src/tyrs/shorter/bitly.py
src/tyrs/shorter/curstom.py
src/tyrs/shorter/googl.py
src/tyrs/shorter/msudpl.py
src/tyrs/shorter/ur1ca.py
src/tyrs/shorter/urlshorter.py
tyrs.egg-info/PKG-INFO
tyrs.egg-info/SOURCES.txt
tyrs.egg-info/dependency_links.txt
tyrs.egg-info/requires.txt
tyrs.egg-info/top_level.txt