Metadata-Version: 1.0
Name: tyrs
Version: 0.6.2
Summary: Twitter and Identica client using curses
Home-page: http://tyrs.nicosphere.net
Author: Nicolas Paris
Author-email: nicolas.caen@gmail.com
License: GPLv3
Platform: linux
Classifier: Development Status :: 4 - Beta
Classifier: Environment :: Console :: Curses
Classifier: Intended Audience :: End Users/Desktop
Classifier: License :: OSI Approved :: GNU General Public License (GPL)
Classifier: Natural Language :: English
Classifier: Operating System :: POSIX :: Linux
Classifier: Programming Language :: Python :: 2
